codebaseassistant/__init__.py
codebaseassistant/dependency.py
codebaseassistant/dependencyManager.py
codebaseassistant/fileCollectionProtocol.py
codebaseassistant-0.1.dist-info/LICENSE
codebaseassistant-0.1.dist-info/METADATA
codebaseassistant-0.1.dist-info/WHEEL
codebaseassistant-0.1.dist-info/top_level.txt
codebaseassistant-0.1.dist-info/RECORD
