Metadata-Version: 2.1
Name: codebaseassistant
Version: 0.1
Summary: An ollama assistant for any and all codebases
Author: Matthew Sanchez
Author-email: 
Classifier: Programming Language :: Python :: 3
Classifier: License :: OSI Approved :: MIT License
Classifier: Operating System :: OS Independent
Requires-Python: >=3.10
License-File: LICENSE
Requires-Dist: chatollama
